.gitignore
MANIFEST.in
README.rst
bootstrap.py
buildout.cfg
setup.py
test.xml
tutu.xml
captionstransformer/__init__.py
captionstransformer/core.py
captionstransformer/registry.py
captionstransformer/sbv.py
captionstransformer/script.py
captionstransformer/srt.py
captionstransformer/transcript.py
captionstransformer/ttml.py
captionstransformer/youtube.py
captionstransformer.egg-info/PKG-INFO
captionstransformer.egg-info/SOURCES.txt
captionstransformer.egg-info/dependency_links.txt
captionstransformer.egg-info/entry_points.txt
captionstransformer.egg-info/not-zip-safe
captionstransformer.egg-info/requires.txt
captionstransformer.egg-info/top_level.txt
captionstransformer/tests/__init__.py
captionstransformer/tests/test_core.py
captionstransformer/tests/test_sbv.py
captionstransformer/tests/test_srt.py
captionstransformer/tests/test_transcript.py
captionstransformer/tests/test_ttml.py
captionstransformer/tests/test_youtube.py
docs/HISTORY.txt
docs/INSTALL.txt
docs/LICENSE.GPL
docs/LICENSE.txt