Metadata-Version: 1.0
Name: captionstransformer
Version: 1.2
Summary: A set of tools (API + script) to read, write and transform captions from/to many formats
Home-page: https://github.com/toutpt/captionstranformer
Author: JeanMichel FRANCOIS aka toutpt
Author-email: toutpt@gmail.com
License: GPL
Keywords: caption subtitle
Platform: UNKNOWN
Classifier: Programming Language :: Python
Classifier: Operating System :: OS Independent
Classifier: License :: OSI Approved :: GNU General Public License (GPL)
